README.md
setup.py
companynameparser/__init__.py
companynameparser/__main__.py
companynameparser/logger.py
companynameparser/parser.py
companynameparser/place.py
companynameparser/tokenizer.py
companynameparser.egg-info/PKG-INFO
companynameparser.egg-info/SOURCES.txt
companynameparser.egg-info/dependency_links.txt
companynameparser.egg-info/requires.txt
companynameparser.egg-info/top_level.txt
companynameparser/../LICENSE
companynameparser/../README.md
companynameparser/../requirements.txt
companynameparser/data/THUOCL_diming.txt
companynameparser/data/brand.txt
companynameparser/data/china_place.txt
companynameparser/data/pca.csv
companynameparser/data/place_single.txt
companynameparser/data/suffix.txt
companynameparser/data/suffix_single.txt
companynameparser/data/trade.txt
companynameparser/data/trade_single.txt
companynameparser/tools/__init__.py
companynameparser/tools/bio_2_entity.py
companynameparser/tools/generate_bio.py