Metadata-Version: 2.1
Name: companynameparser
Version: 0.1.8
Summary: Chinese Company Name Parser and Extraction Tool,Company name Recognition Utilities
Home-page: https://github.com/shibing624/companynameparser
Author: XuMing
Author-email: xuming624@qq.com
License: Apache License 2.0
Keywords: NLP,Simplified Chinese,Chinese geographic information
Platform: UNKNOWN
Classifier: Intended Audience :: Developers
Classifier: Operating System :: OS Independent
Classifier: Natural Language :: Chinese (Simplified)
Classifier: Natural Language :: Chinese (Traditional)
Classifier: Programming Language :: Python
Classifier: Programming Language :: Python :: 3
Classifier: Programming Language :: Python :: 3.5
Classifier: Programming Language :: Python :: 3.6
Classifier: Programming Language :: Python :: 3.7
Classifier: Programming Language :: Python :: 3.8
Classifier: Topic :: Text Processing
Classifier: Topic :: Text Processing :: Indexing
Classifier: Topic :: Text Processing :: Linguistic
